example_package/__init__.py
teamgun/__init__.py
teamgun1-0.1.3.dist-info/METADATA
teamgun1-0.1.3.dist-info/WHEEL
teamgun1-0.1.3.dist-info/entry_points.txt
teamgun1/.pytest_cache/.gitignore
teamgun1/.pytest_cache/CACHEDIR.TAG
teamgun1/.pytest_cache/README.md
teamgun1/.pytest_cache/v/cache/nodeids
teamgun1/.pytest_cache/v/cache/stepwise
teamgun1/__init__.py
teamgun1/news.py
teamgun1/weather_show.py
teamgun1-0.1.3.dist-info/RECORD
